d4kms_generic/__init__.py
d4kms_generic/auth0_management.py
d4kms_generic/auth0_service.py
d4kms_generic/errors.py
d4kms_generic/logger.py
d4kms_generic/service.py
d4kms_generic/service_environment.py
d4kms_info/__init__.py
d4kms_service/__init__.py
d4kms_service/neo4j_connection.py
d4kms_service/node.py
d4kms_ui/__init__.py
d4kms_ui/github.py
d4kms_ui/markdown_page.py
d4kms_ui/pagination.py
d4kms_ui/release_notes.py
d4kms-0.14.dist-info/LICENSE
d4kms-0.14.dist-info/METADATA
d4kms-0.14.dist-info/WHEEL
d4kms-0.14.dist-info/top_level.txt
d4kms-0.14.dist-info/RECORD
