Metadata-Version: 2.1
Name: d4kms
Version: 0.14
Summary: A python package for building d4k microservcies
Author: D Iberson-Hurst
Author-email: 
Classifier: Intended Audience :: Developers
Classifier: Programming Language :: Python
Classifier: Programming Language :: Python :: 3
Classifier: Programming Language :: Python :: 3.10
Classifier: Operating System :: OS Independent
License-File: LICENSE
Requires-Dist: pydantic
Requires-Dist: requests
Requires-Dist: pyyaml
Requires-Dist: python-dotenv
Requires-Dist: neo4j
Requires-Dist: markdown
Requires-Dist: fastapi
Requires-Dist: Authlib
Requires-Dist: starlette
Requires-Dist: itsdangerous
Requires-Dist: auth0-python
